EnergyScan/__init__.py
EnergyScan/config.py
EnergyScan/main.py
EnergyScan/data_sources/__init__.py
EnergyScan/data_sources/apple_store.py
EnergyScan/data_sources/flathub.py
EnergyScan/data_sources/gog.py
EnergyScan/data_sources/itch_io.py
EnergyScan/data_sources/myabandonware.py
EnergyScan/data_sources/snap.py
EnergyScan-0.1.0.dist-info/METADATA
EnergyScan-0.1.0.dist-info/WHEEL
EnergyScan-0.1.0.dist-info/entry_points.txt
EnergyScan-0.1.0.dist-info/top_level.txt
EnergyScan-0.1.0.dist-info/RECORD
