Metadata-Version: 2.1
Name: EnergyScan
Version: 0.1.0
Requires-Dist: beautifulsoup4 ==4.13.4
Requires-Dist: Requests ==2.32.4
Requires-Dist: selenium ==4.33.0
